<?xml version="1.0" encoding="UTF-8" ?>
<!DOCTYPE mapper
        PUBLIC "-//mybatis.org//DTD Mapper 3.0//EN"
        "https://mybatis.org/dtd/mybatis-3-mapper.dtd">
<mapper namespace="bitcamp.myapp.dao.MyPageDao">

    <resultMap type="myPage" id="myPageMap">
        <id column="mno" property="no"/>
        <result column="nick" property="nick"/>
        <result column="name" property="name"/>
        <result column="phone_number" property="phoneNumber"/>
        <result column="password" property="password"/>
        <result column="email" property="email"/>
        <result column="filepath" property="photo"/>
        <result column="state_message" property="stateMessage"/>
        <result column="birthday" property="birthday"/>
        <result column="gender" property="gender"/>
        <result column="likes" property="likes"/>
        <result column="visit_count" property="visitCount"/>
        <result column="created_date" property="createdDate"/>
    </resultMap>

    <resultMap type="member" id="memberMap">
        <id column="mno" property="no"/>
        <result column="nick" property="nick"/>
        <result column="name" property="name"/>
        <result column="phone_number" property="phoneNumber"/>
        <result column="email" property="email"/>
        <result column="password" property="password"/>
        <result column="filepath" property="photo"/>
    </resultMap>

    <insert id="insert" parameterType="myPage">
        insert into sns_mypage(state_message, birthday, gender)
        values(#{state_message}, #{birthday}, #{gender})
    </insert>

    <select id="findBy" parameterType="int" resultMap="myPageMap">
        select
        mp.mno
        ,nick
        ,name
        ,phone_number
        ,email
        ,filepath
        ,state_message
        ,birthday
        ,gender
        ,likes
        ,visit_count
        ,created_date
        from
        sns_mypage as mp inner join sns_member as m on mp.mno=m.mno
        where
        mp.mno=#{memberNo}
    </select>

    <update id="update" parameterType="myPage">
        update sns_mypage set
        state_message=#{stateMessage}
        ,birthday=#{birthday}
        ,gender=#{gender}
        where
        mno=#{no}
    </update>

    <delete id="delete" parameterType="int">
        delete from sns_mypage
        where
        mno=#{memberNo}
    </delete>


    <insert id="insertFollow">
        insert into sns_follow(follower, following)
        values(#{followerNo}, #{followingNo})
    </insert>

    <delete id="deleteFollow">
        delete from sns_follow
        where
        follower=#{followerNo}
        and following=#{followingNo}
    </delete>

    <select id="findAllFollowers" parameterType="int" resultMap="memberMap">
        select
        m.mno
        ,m.nick
        ,m.name
        ,m.phone_number
        ,m.email
        ,m.filepath
        from
        (select follower
        from sns_follow
        where following=#{memberNo}) as f
        inner join sns_member as m on f.follower=m.mno
    </select>

    <select id="findAllFollowings" parameterType="int" resultMap="memberMap">
        select
        m.mno
        ,m.nick
        ,m.name
        ,m.phone_number
        ,m.email
        ,m.filepath
        from
        (select following
        from sns_follow
        where follower=#{memberNo}) as f
        inner join sns_member as m on f.following=m.mno
    </select>
</mapper>